clireg/__init__.py
clireg/core.py
clireg/datasets.py
clireg/features.py
clireg/graph.py
clireg/io.py
clireg/pipeline.py
clireg/types.py
clireg/utils.py
clireg/vis.py
clireg/config/__init__.py
clireg/config/config.py
clireg/pybind/clireg_pybind.cpython-312-aarch64-linux-gnu.so
clireg/pybind/include/gmock/gmock-actions.h
clireg/pybind/include/gmock/gmock-cardinalities.h
clireg/pybind/include/gmock/gmock-function-mocker.h
clireg/pybind/include/gmock/gmock-matchers.h
clireg/pybind/include/gmock/gmock-more-actions.h
clireg/pybind/include/gmock/gmock-more-matchers.h
clireg/pybind/include/gmock/gmock-nice-strict.h
clireg/pybind/include/gmock/gmock-spec-builders.h
clireg/pybind/include/gmock/gmock.h
clireg/pybind/include/gmock/internal/gmock-internal-utils.h
clireg/pybind/include/gmock/internal/gmock-port.h
clireg/pybind/include/gmock/internal/gmock-pp.h
clireg/pybind/include/gmock/internal/custom/README.md
clireg/pybind/include/gmock/internal/custom/gmock-generated-actions.h
clireg/pybind/include/gmock/internal/custom/gmock-matchers.h
clireg/pybind/include/gmock/internal/custom/gmock-port.h
clireg/pybind/include/gtest/gtest-assertion-result.h
clireg/pybind/include/gtest/gtest-death-test.h
clireg/pybind/include/gtest/gtest-matchers.h
clireg/pybind/include/gtest/gtest-message.h
clireg/pybind/include/gtest/gtest-param-test.h
clireg/pybind/include/gtest/gtest-printers.h
clireg/pybind/include/gtest/gtest-spi.h
clireg/pybind/include/gtest/gtest-test-part.h
clireg/pybind/include/gtest/gtest-typed-test.h
clireg/pybind/include/gtest/gtest.h
clireg/pybind/include/gtest/gtest_pred_impl.h
clireg/pybind/include/gtest/gtest_prod.h
clireg/pybind/include/gtest/internal/gtest-death-test-internal.h
clireg/pybind/include/gtest/internal/gtest-filepath.h
clireg/pybind/include/gtest/internal/gtest-internal.h
clireg/pybind/include/gtest/internal/gtest-param-util.h
clireg/pybind/include/gtest/internal/gtest-port-arch.h
clireg-1.0.4.dist-info/METADATA
clireg-1.0.4.dist-info/WHEEL
clireg-1.0.4.dist-info/entry_points.txt
clireg-1.0.4.dist-info/RECORD
clireg-1.0.4.dist-info/licenses/LICENSE
clireg-1.0.4.dist-info/sboms/auditwheel.cdx.json
